rust_add_pyo3-0.1.0.dist-info/METADATA
rust_add_pyo3-0.1.0.dist-info/WHEEL
rust_add_pyo3/__init__.py
rust_add_pyo3/rust_add_pyo3.abi3.so
rust_add_pyo3-0.1.0.dist-info/RECORD
